{
    "patches":
    [
        {
            "patternBytes": "32 31 39 2e 36 32 2e 31 35 00 00 00 00 00 00 00 00",
            "patchBytes": "36",
            "patchOffset": "8",
            "secondMatchCorrelation": "0.6686279177665710449",
            "adjustedSecondMatchCorrelation": "0.6046173877904873484",
            "comment": "Original offset: 28f"
        },
        {
            "patternBytes": "5c f9 f2 5f 4e f7 f2 5f 65 f9 f2 5f 44 f7 f2 5f 6c f9",
            "patchBytes": "dd f7",
            "patchOffset": "8",
            "secondMatchCorrelation": "0.8070511221885681152",
            "adjustedSecondMatchCorrelation": "0.7649381253270384207",
            "comment": "Original offset: 1030"
        },
        {
            "patternBytes": "ff f7 60 fb ef f5 f2 5f 29 fa f2 5f e8 f4 f2 5f 2f fa",
            "patchBytes": "6e f9",
            "patchOffset": "8",
            "secondMatchCorrelation": "0.6662120223045349121",
            "adjustedSecondMatchCorrelation": "0.6018878575772702577",
            "comment": "Original offset: 11d4"
        },
        {
            "patternBytes": "01 22 0d ab 30 46 21 46 ff f7 50 fb b8 b1 4f f0 ff 36 01 28",
            "patchBytes": "00 20 18 60",
            "patchOffset": "8",
            "secondMatchCorrelation": "0.5838332772254943848",
            "adjustedSecondMatchCorrelation": "0.5103417006223911478",
            "comment": "Original offset: 14fe0"
        },
        {
            "patternBytes": "fc f7 70 fe 38 b1 20 20 04 f0 90 fc 00 28 1e bf 13 98 01 21",
            "patchBytes": "01 20 01 20",
            "patchOffset": "8",
            "secondMatchCorrelation": "0.7039383649826049805",
            "adjustedSecondMatchCorrelation": "0.6447900007080273888",
            "comment": "Original offset: 155e0"
        },
        {
            "patternBytes": "2c 68 0d a9 01 f0 e3 f9 96 49 00 2c 08 bf 0e 46 b0",
            "patchBytes": "95",
            "patchOffset": "8",
            "secondMatchCorrelation": "0.5077779293060302734",
            "adjustedSecondMatchCorrelation": "0.4286395845049944531",
            "comment": "Original offset: 162ba"
        },
        {
            "patternBytes": "20 de f3 5f c8 ac f3 5f 0b 3d f3 5f a6 fd f2 5f 33 3d",
            "patchBytes": "d8 99",
            "patchOffset": "8",
            "secondMatchCorrelation": "0.6922338008880615234",
            "adjustedSecondMatchCorrelation": "0.6314166095225496322",
            "comment": "Original offset: 16510"
        },
        {
            "patternBytes": "73 00 66 61 6c 73 65 00 32 00 66 61 69 6c 65 64 20",
            "patchBytes": "34",
            "patchOffset": "8",
            "secondMatchCorrelation": "0.647272646427154541",
            "adjustedSecondMatchCorrelation": "0.580575985165663333",
            "comment": "Original offset: 2fa2f"
        },
        {
            "patternBytes": "32 31 39 2e 36 32 2e 31 35 00 72 6f 6f 74 2d 74 69",
            "patchBytes": "36",
            "patchOffset": "8",
            "secondMatchCorrelation": "0.6686279177665710449",
            "adjustedSecondMatchCorrelation": "0.6046173877904873484",
            "comment": "Original offset: 3385d"
        },
        {
            "patternBytes": "30 06 30 06 12 02 30 06 30 06 30 06 12 02 30 06 30 06 30 06 30 06 30 06 30 06 1e 00 1e 00 30 06 30 06",
            "patchBytes": "b0 07",
            "patchOffset": "16",
            "secondMatchCorrelation": "0.8912355899810791016",
            "adjustedSecondMatchCorrelation": "0.7943008768489221438",
            "comment": "Original offset: 38b1e"
        },
        {
            "patternBytes": "52 65 6c 69 61 6e 63 65 20 6f 6e 20 74 68 69 73 20 63 65 72 74 69 66 69 63 61 74 65 20 62 79 20 61 6e 79 20 70 61 72 74 79 20 61 73 73 75 6d 65 73 20 61",
            "patchBytes": "72 64 3d 64 69 73 6b 30 73 31 73 35 20 2d 76 20 61 6d 66 69 3d 30 78 66 66 20 63 73 5f 65 6e 66 6f 72 63 65 6d 65 6e 74 5f 64 69 73 61 62 6c 65 3d 31 00",
            "patchOffset": "0",
            "secondMatchCorrelation": "0.568627476692199707",
            "adjustedSecondMatchCorrelation": "0.568627476692199707",
            "comment": "Original offset: 399d8"
        },
        {
            "patternBytes": "00 00 00 00 00 00 00 00 52 b4 28 30 b6 9d 63 f7 96 fe c4 68 5c 52 bb aa 00 00 00 00 00 00 00 00",
            "patchBytes": "c8 54 36 00 39 78 81 44 ee d2 3f 9b 38 31 22 68",
            "patchOffset": "8",
            "secondMatchCorrelation": "0.4046230018138885498",
            "adjustedSecondMatchCorrelation": "0.3227105842600213603",
            "comment": "Original offset: 3b000"
        }
    ]
}
